examples/LED_knob.py
examples/ad_example.py
examples/ad_example_duo.py
examples/ad_experiments.py
examples/da_example.py
examples/da_example_duo.py
examples/da_experiments.py
examples/full_example.py
original-AD/ADS1256_default_config.py
original-AD/ADS1256_definitions.py
original-AD/__init__.py
original-AD/bench_config.py
original-AD/benchmark.py
original-AD/example.py
original-AD/example_2.py
original-AD/pipyadc.py
original-AD/simpletest.py
original-DA/DAC8552_default_config.py
original-DA/__init__.py
original-DA/dac8552.py
original-DA/example.py
waveshare/__init__.py
waveshare/definitions.py
waveshare/ADS1256/__init__.py
waveshare/ADS1256/default_config.py
waveshare/ADS1256/definitions.py
waveshare/ADS1256/pigpio.py
waveshare/DAC8552/__init__.py
waveshare/DAC8552/default_config.py
waveshare/DAC8552/pigpio.py
waveshare_d2a_a2d_pigpio-1.0.1.dist-info/METADATA
waveshare_d2a_a2d_pigpio-1.0.1.dist-info/WHEEL
waveshare_d2a_a2d_pigpio-1.0.1.dist-info/top_level.txt
waveshare_d2a_a2d_pigpio-1.0.1.dist-info/RECORD
