Metadata-Version: 2.1
Name: waveshare-d2a-a2d-pigpio
Version: 1.0.1
Summary: Python PiGPIO interface to Raspberry Pi Waveshare A2D/D2A Card
Home-page: https://github.com/the-moog/waveshare_a2d_d2a_python
Author: Jason Morgan, largely based on work by Mitch Kahn
Author-email: pypy@cropwell.net
License: https://github.com/makahn64/waveshare_a2d_d2a_python
Platform: UNKNOWN
Requires-Python: >=3.7
Requires-Dist: pigpio
Requires-Dist: blessings
